<?xml version="1.0" encoding="UTF-8" standalone="no"?>
<!DOCTYPE tiles-definitions PUBLIC "-//Apache Software Foundation//DTD Tiles Configuration 2.1//EN" "http://tiles.apache.org/dtds/tiles-config_2_1.dtd">
<tiles-definitions>
    <definition extends="default" name="ssiarticulounidadmedidas/list">
        <put-attribute name="body" value="/WEB-INF/views/ssiarticulounidadmedidas/list.jspx"/>
    </definition>
<definition extends="default" name="ssiarticulounidadmedidas/show">
        <put-attribute name="body" value="/WEB-INF/views/ssiarticulounidadmedidas/show.jspx"/>
    </definition>
<definition extends="default" name="ssiarticulounidadmedidas/create">
        <put-attribute name="body" value="/WEB-INF/views/ssiarticulounidadmedidas/create.jspx"/>
    </definition>
<definition extends="default" name="ssiarticulounidadmedidas/update">
        <put-attribute name="body" value="/WEB-INF/views/ssiarticulounidadmedidas/update.jspx"/>
    </definition>
</tiles-definitions>
